pytorch_h5dataset/__init__.py
pytorch_h5dataset/_h5dataset.py
pytorch_h5dataset/utils.py
pytorch_h5dataset/benchmark/__init__.py
pytorch_h5dataset/benchmark/benchmardataset.py
pytorch_h5dataset/benchmark/benchmarker.py
pytorch_h5dataset/dataloader/__init__.py
pytorch_h5dataset/dataloader/daliDataLoader.py
pytorch_h5dataset/dataloader/dataLoader.py
pytorch_h5dataset/dataset/__init__.py
pytorch_h5dataset/dataset/bloscDataset.py
pytorch_h5dataset/dataset/imageDataset.py
pytorch_h5dataset/dataset/metaDataset.py
pytorch_h5dataset/fn/__init__.py
pytorch_h5dataset/fn/blosc.py
pytorch_h5dataset/fn/crop.py
pytorch_h5dataset/fn/crop_params.py
pytorch_h5dataset/fn/data_interface.py
pytorch_h5dataset/fn/image.py
pytorch_h5dataset/fn/transforms.py
pytorch_h5dataset-0.2.4.dist-info/LICENSE
pytorch_h5dataset-0.2.4.dist-info/METADATA
pytorch_h5dataset-0.2.4.dist-info/WHEEL
pytorch_h5dataset-0.2.4.dist-info/top_level.txt
pytorch_h5dataset-0.2.4.dist-info/RECORD
