Metadata-Version: 2.1
Name: pytorch-h5dataset
Version: 0.2.4
Summary: Accelerated data loading H5 dataset module for  PyTorch.
Home-page: https://github.com/CeadeS/PyTorchH5Dataset
Author: Martin Hofmann
Author-email: Martin.Hofmann@tu-ilmenau.de
License: BSD-3-Clause License
Platform: UNKNOWN
Classifier: Development Status :: 4 - Beta
Classifier: Intended Audience :: Developers
Classifier: Intended Audience :: Education
Classifier: Intended Audience :: Science/Research
Classifier: License :: OSI Approved :: BSD License
Classifier: Operating System :: POSIX :: Linux
Classifier: Operating System :: Microsoft :: Windows :: Windows 10
Classifier: Programming Language :: Python :: 3
Classifier: Programming Language :: Python :: 3.7
Classifier: Programming Language :: Python :: 3.9
Classifier: Programming Language :: Python :: 3.10
License-File: LICENSE
Requires-Dist: numpy
Requires-Dist: h5py (>=3.3.0)
Requires-Dist: hdf5plugin
Requires-Dist: pandas
Requires-Dist: Pillow
Requires-Dist: tables
Requires-Dist: torch
Requires-Dist: scikit-image
Requires-Dist: torchvision
Requires-Dist: psutil
Requires-Dist: tqdm
